kmdouglass/udesigner/__init__.py
kmdouglass/udesigner/dpm.py
kmdouglass/udesigner/mfki.py
kmdouglass/udesigner/scripts/udesign.py
kmdouglass/udesigner/templates/dpm_design.html
kmdouglass/udesigner/templates/mfki_design.html
kmdouglass/udesigner/udesigner.py
kmdouglass_udesigner-0.1.0.dist-info/LICENSE
kmdouglass_udesigner-0.1.0.dist-info/METADATA
kmdouglass_udesigner-0.1.0.dist-info/WHEEL
kmdouglass_udesigner-0.1.0.dist-info/entry_points.txt
kmdouglass_udesigner-0.1.0.dist-info/RECORD
