Metadata-Version: 2.1
Name: kmdouglass.udesigner
Version: 0.1.0
Summary: Design tools for microscopes
Home-page: https://github.com/kmdouglass/micro-designer
License: MIT
Author: Kyle M. Douglass
Author-email: kyle.m.douglass@gmail.com
Requires-Python: >=3.8,<4.0
Classifier: License :: OSI Approved :: MIT License
Classifier: Programming Language :: Python :: 3
Classifier: Programming Language :: Python :: 3.8
Classifier: Programming Language :: Python :: 3.9
Classifier: Programming Language :: Python :: 3.10
Classifier: Programming Language :: Python :: 3.11
Requires-Dist: Jinja2
Requires-Dist: aenum
Requires-Dist: matplotlib
Project-URL: Repository, https://github.com/kmdouglass/micro-designer
